MANIFEST.in
README.rst
icon.gif
icon.png
setup.py
ctdl/__init__.py
ctdl/ctdl.py
ctdl/downloader.py
ctdl/gui.py
ctdl/gui_downloader.py
ctdl/utils.py
ctdl.egg-info/PKG-INFO
ctdl.egg-info/SOURCES.txt
ctdl.egg-info/dependency_links.txt
ctdl.egg-info/entry_points.txt
ctdl.egg-info/not-zip-safe
ctdl.egg-info/requires.txt
ctdl.egg-info/top_level.txt