Metadata-Version: 1.1
Name: ctdl
Version: 1.5.0
Summary: Bulk file downloader on any topic.
Home-page: https://github.com/nikhilkumarsingh/content-downloader
Author: Nikhil Kumar Singh
Author-email: nikhilksingh97@gmail.com
License: MIT
Keywords: content downloader bulk files
Platform: UNKNOWN
Classifier: Development Status :: 4 - Beta
Classifier: License :: OSI Approved :: MIT License
Classifier: Programming Language :: Python
Classifier: Programming Language :: Python :: 2
Classifier: Programming Language :: Python :: 2.6
Classifier: Programming Language :: Python :: 2.7
Classifier: Programming Language :: Python :: 3
Classifier: Programming Language :: Python :: 3.3
Classifier: Programming Language :: Python :: 3.4
Classifier: Programming Language :: Python :: 3.5
Classifier: Topic :: Internet
